yolo_world_utils/__init__.py
yolo_world_utils/__main__.py
yolo_world_utils/bpe_simple_vocab_16e6.txt
yolo_world_utils/feature_generate.py
yolo_world_utils/simple_tokenizer.py
yolo_world_utils-1.0.2.dist-info/METADATA
yolo_world_utils-1.0.2.dist-info/WHEEL
yolo_world_utils-1.0.2.dist-info/top_level.txt
yolo_world_utils-1.0.2.dist-info/RECORD
