Metadata-Version: 2.4
Name: yolo-world-utils
Version: 1.0.2
Summary: tools for yolo-world, like generate input token from string, or generate text feature
Author-email: Neucrack <czd666666@gmail.com>
Requires-Dist: ftfy
Requires-Dist: regex
Requires-Dist: onnxruntime
